mib/__init__.py
mib/source.py
mib/theme.py
mib_notebook-0.1.2.dist-info/METADATA
mib_notebook-0.1.2.dist-info/WHEEL
mib_notebook-0.1.2.dist-info/licenses/LICENSE
mib_notebook-0.1.2.dist-info/RECORD
