Metadata-Version: 2.4
Name: mib-notebook
Version: 0.1.2
Summary: A literate programming tool for static notebook as a library
Project-URL: repository, https://github.com/pietroppeter/mib
Project-URL: issue-tracker, https://github.com/pietroppeter/mib/issues
Author: Pietro Peterlongo
License-Expression: MIT
License-File: LICENSE
Classifier: License :: OSI Approved :: MIT License
Classifier: Operating System :: OS Independent
Classifier: Programming Language :: Python :: 3
Requires-Python: >=3.9
Requires-Dist: markdown>=3.7
Requires-Dist: pydantic>=2.10.6
